experiments/__init__.py
experiments/eq.py
experiments/experiment.py
experiments/mauna_loa.py
experiments/smk.py
experiments/paper/README.md
experiments/paper/compare_inference.py
experiments/paper/comparison.py
experiments/paper/comparison_process.py
experiments/paper/crude_oil.py
experiments/paper/crude_oil_aggregate.py
experiments/paper/priors.py
experiments/paper/reproduce.sh
experiments/paper/requirements_snapshot.txt
experiments/paper/sample.py
experiments/paper/sample_interpolation.py
experiments/paper/smk.py
experiments/paper/vix_analyse.py
experiments/paper/vix_forecast.py
experiments/paper/vix_forecast_process.py
gpcm/__init__.py
gpcm/_version.py
gpcm/approx.py
gpcm/exppoly.py
gpcm/gpcm.py
gpcm/model.py
gpcm/normal.py
gpcm/rgpcm.py
gpcm/sample.py
gpcm/util.py
tests/__init__.py
tests/test_exppoly.py
tests/test_gpcm.py
tests/test_model.py
tests/test_normal.py
tests/test_rgpcm.py
tests/test_sample.py
tests/util.py
gpcm-0.2.0.dist-info/LICENCE.txt
gpcm-0.2.0.dist-info/METADATA
gpcm-0.2.0.dist-info/WHEEL
gpcm-0.2.0.dist-info/top_level.txt
gpcm-0.2.0.dist-info/RECORD
