Metadata-Version: 2.1
Name: gpcm
Version: 0.2.0
Summary: Implementation of the GPCM and variations
Home-page: https://github.com/wesselb/gpcm
Author: Wessel Bruinsma
Author-email: wessel.p.bruinsma@gmail.com
License: MIT
Requires-Python: >=3.6
License-File: LICENCE.txt
Requires-Dist: numpy (>=1.16)
Requires-Dist: scipy
Requires-Dist: matplotlib
Requires-Dist: plum-dispatch (>=2)
Requires-Dist: backends (>=1.4.9)
Requires-Dist: backends-matrix (>=1.1.5)
Requires-Dist: stheno (>=1.1.7)
Requires-Dist: mlkernels (>=0.3.3)
Requires-Dist: varz (>=0.7.4)
Requires-Dist: wbml (>=0.3.15)
Requires-Dist: probmods (>=0.3.0)
Requires-Dist: jax
Requires-Dist: jaxlib
